mazegen/__init__.py
mazegen/__main__.py
mazegen/cell.py
mazegen/generator.py
mazegen/maze.py
mazegen/solver.py
mazegen/view.py
mazegen-0.0.2.dist-info/METADATA
mazegen-0.0.2.dist-info/WHEEL
mazegen-0.0.2.dist-info/entry_points.txt
mazegen-0.0.2.dist-info/top_level.txt
mazegen-0.0.2.dist-info/RECORD
