Metadata-Version: 2.1
Name: mazegen
Version: 0.0.2
Summary: Python utility to generate and solve mazes.
Home-page: https://github.com/ujjujjuj/mazegen
Author: Ujjwal Dimri
Author-email: ujjwaldimri123@gmail.com
License: UNKNOWN
Project-URL: Documentation, https://github.com/ujjujjuj/mazegen/README.md
Project-URL: Source, https://github.com/ujjujjuj/mazegen
Platform: UNKNOWN
Classifier: Programming Language :: Python :: 3
Classifier: License :: OSI Approved :: MIT License
Classifier: Operating System :: OS Independent
Requires-Python: >=3.6
